Fotofy/Blender.py
Fotofy/Brush.py
Fotofy/EditWindow.py
Fotofy/FileManager.py
Fotofy/Filters.py
Fotofy/Image.py
Fotofy/Tracker.py
Fotofy/__init__.py
Fotofy/__main__.py
fotofy_cv-1.0.0.dist-info/METADATA
fotofy_cv-1.0.0.dist-info/WHEEL
fotofy_cv-1.0.0.dist-info/entry_points.txt
fotofy_cv-1.0.0.dist-info/top_level.txt
fotofy_cv-1.0.0.dist-info/RECORD
