Metadata-Version: 2.1
Name: fotofy-cv
Version: 1.0.0
Summary: UNKNOWN
Home-page: https://github.com/greenLadros/Fotofy-Framework
Author: Ivri Korem
Author-email: ivri.korem@gmail.com
License: MIT
Platform: UNKNOWN
Classifier: License :: OSI Approved :: MIT License
Classifier: Programming Language :: Python :: 3
Classifier: Programming Language :: Python :: 3.8
Classifier: Programming Language :: Python :: 3.9
Requires-Dist: numpy
Requires-Dist: matplotlib
Requires-Dist: opencv-python
